degann/__init__.py
degann/equations/__init__.py
degann/equations/equation_utils.py
degann/equations/simple_equation.py
degann/equations/system_ode.py
degann/expert/__init__.py
degann/expert/pipeline.py
degann/expert/selector.py
degann/networks/__init__.py
degann/networks/activations.py
degann/networks/callbacks.py
degann/networks/config_format.py
degann/networks/cpp_utils.py
degann/networks/imodel.py
degann/networks/layer_creator.py
degann/networks/losses.py
degann/networks/metrics.py
degann/networks/optimizers.py
degann/networks/utils.py
degann/networks/layers/__init__.py
degann/networks/layers/tf_dense.py
degann/networks/topology/__init__.py
degann/networks/topology/tf_densenet.py
degann/search_algorithms/__init__.py
degann/search_algorithms/generate.py
degann/search_algorithms/grid_search.py
degann/search_algorithms/nn_code.py
degann/search_algorithms/pattern_search.py
degann/search_algorithms/random_search.py
degann/search_algorithms/simulated_annealing.py
degann/search_algorithms/utils.py
degann-1.1.5.dist-info/LICENSE
degann-1.1.5.dist-info/METADATA
degann-1.1.5.dist-info/WHEEL
degann-1.1.5.dist-info/top_level.txt
degann-1.1.5.dist-info/RECORD
