Metadata-Version: 2.1
Name: degann
Version: 1.1.5
Summary: Library for generating artificial neural networks for modeling the behavior of dynamic systems
Home-page: https://github.com/Krekep/degann
Author: Pavel Alimov
Author-email: <pashaalimov@gmail.com>
License: MIT
Keywords: python,ode,differential equation,neural network
Classifier: Development Status :: 5 - Production/Stable
Classifier: Intended Audience :: Education
Classifier: Intended Audience :: Science/Research
Classifier: License :: OSI Approved :: MIT License
Classifier: Operating System :: POSIX :: Linux
Classifier: Operating System :: Microsoft :: Windows
Classifier: Programming Language :: Python :: 3
Classifier: Topic :: Scientific/Engineering :: Physics
Requires-Python: >=3.10
License-File: LICENSE
Requires-Dist: keras (~=3.3.3)
Requires-Dist: matplotlib (~=3.7.1)
Requires-Dist: numpy (~=1.26.4)
Requires-Dist: scipy (~=1.13.1)
Requires-Dist: tensorflow (~=2.16.1)
